cepcenv/CEPCENV_VERSION
cepcenv/__init__.py
cepcenv/check.py
cepcenv/env.py
cepcenv/git.py
cepcenv/loader.py
cepcenv/logger.py
cepcenv/package_manager.py
cepcenv/util.py
cepcenv/cmd/__init__.py
cepcenv/cmd/clean.py
cepcenv/cmd/config.py
cepcenv/cmd/config_release.py
cepcenv/cmd/config_version.py
cepcenv/cmd/exit.py
cepcenv/cmd/home.py
cepcenv/cmd/init.py
cepcenv/cmd/install.py
cepcenv/cmd/ls.py
cepcenv/cmd/ls_env.py
cepcenv/cmd/ls_package.py
cepcenv/cmd/ls_remote.py
cepcenv/cmd/pack.py
cepcenv/cmd/platform.py
cepcenv/cmd/upgrade.py
cepcenv/cmd/use.py
cepcenv/cmd/version.py
cepcenv/config/__init__.py
cepcenv/config/config_release.py
cepcenv/config/config_version.py
cepcenv/config/info.py
cepcenv/config/main.py
cepcenv/install/__init__.py
cepcenv/install/executor.py
cepcenv/install/release.py
cepcenv/install/selector.py
cepcenv/platform/__init__.py
cepcenv/shell/__init__.py
cepcenv/shell/base.py
cepcenv/shell/cepcenv.csh
cepcenv/shell/cepcenv_script.csh
cepcenv/shell/csh.py
cepcenv/shell/sh.py
cepcenv/support/cepcenv.conf.example
cepcenv/use/__init__.py
cepcenv-0.2.2.dist-info/METADATA
cepcenv-0.2.2.dist-info/WHEEL
cepcenv-0.2.2.dist-info/entry_points.txt
cepcenv-0.2.2.dist-info/top_level.txt
cepcenv-0.2.2.dist-info/RECORD
