Metadata-Version: 2.1
Name: cepcenv
Version: 0.2.2
Summary: CEPC software management toolkit
Home-page: https://github.com/cepc/cepcenv
Author: Xianghu Zhao
Author-email: zhaoxh@ihep.ac.cn
License: MIT
Keywords: CEPC
Platform: UNKNOWN
Classifier: Development Status :: 5 - Production/Stable
Classifier: Intended Audience :: Science/Research
Classifier: Topic :: Scientific/Engineering :: Physics
Classifier: Topic :: System :: Software Distribution
Classifier: License :: OSI Approved :: MIT License
Classifier: Programming Language :: Python :: 2
Classifier: Programming Language :: Python :: 2.6
Classifier: Programming Language :: Python :: 2.7
Classifier: Programming Language :: Python :: 3
Classifier: Programming Language :: Python :: 3.3
Classifier: Programming Language :: Python :: 3.4
Classifier: Programming Language :: Python :: 3.5
Classifier: Programming Language :: Python :: 3.6
Classifier: Programming Language :: Python :: Implementation :: CPython
Classifier: Programming Language :: Python :: Implementation :: PyPy
Requires-Dist: paradag (<=0.2.0)
Requires-Dist: click (<7.0,>=6.0)
Requires-Dist: PyYAML (<4.0,>=3.0)
Requires-Dist: distro
